googledoc/__init__.py
googledoc/docscrape_google.py
googledoc-0.1.0.dist-info/METADATA
googledoc-0.1.0.dist-info/WHEEL
googledoc-0.1.0.dist-info/top_level.txt
googledoc-0.1.0.dist-info/RECORD
