Metadata-Version: 2.1
Name: googledoc
Version: 0.1.0
Summary: A module cut from xcookie
Home-page: UNKNOWN
Author: joncrall
Author-email: jon.crall@kitware.com
License: Apache 2
Platform: UNKNOWN
Classifier: Development Status :: 1 - Planning
Classifier: Intended Audience :: Developers
Classifier: Topic :: Software Development :: Libraries :: Python Modules
Classifier: Topic :: Utilities
Classifier: License :: OSI Approved :: Apache Software License
Classifier: Programming Language :: Python :: 3.7
Classifier: Programming Language :: Python :: 3.8
Classifier: Programming Language :: Python :: 3.9
Classifier: Programming Language :: Python :: 3.10
Requires-Python: >=3.7
Provides-Extra: all
Requires-Dist: codecov ; extra == 'all'
Requires-Dist: pytest-timeout ; extra == 'all'
Requires-Dist: xdoctest ; extra == 'all'
Provides-Extra: all-strict
Requires-Dist: codecov (==2.0.15) ; extra == 'all-strict'
Requires-Dist: pytest-timeout (==1.4.2) ; extra == 'all-strict'
Requires-Dist: xdoctest (==0.15.0) ; extra == 'all-strict'
Requires-Dist: coverage (==4.5) ; (python_version < "2.7" and python_version >= "2.6") and extra == 'all-strict'
Requires-Dist: pytest-cov (==2.8.1) ; (python_version < "2.8.0" and python_version >= "2.7.0") and extra == 'all-strict'
Requires-Dist: pytest (<=4.6.11,==4.6.0) ; (python_version < "2.8.0" and python_version >= "2.7.0") and extra == 'all-strict'
Requires-Dist: coverage (==5.3.1) ; (python_version < "3.10" and python_version >= "3.9") and extra == 'all-strict'
Requires-Dist: pytest (==4.6.0) ; (python_version < "3.10.0" and python_version >= "3.7.0") and extra == 'all-strict'
Requires-Dist: coverage (==5.3.1) ; (python_version < "3.4" and python_version >= "2.7") and extra == 'all-strict'
Requires-Dist: coverage (==4.3.4) ; (python_version < "3.5" and python_version >= "3.4") and extra == 'all-strict'
Requires-Dist: pytest-cov (==2.8.1) ; (python_version < "3.5.0" and python_version >= "3.4.0") and extra == 'all-strict'
Requires-Dist: pytest (<=4.6.11,==4.6.0) ; (python_version < "3.5.0" and python_version >= "3.4.0") and extra == 'all-strict'
Requires-Dist: coverage (==5.3.1) ; (python_version < "3.6" and python_version >= "3.5") and extra == 'all-strict'
Requires-Dist: pytest-cov (==2.9.0) ; (python_version < "3.6.0" and python_version >= "3.5.0") and extra == 'all-strict'
Requires-Dist: pytest (<=6.1.2,==4.6.0) ; (python_version < "3.6.0" and python_version >= "3.5.0") and extra == 'all-strict'
Requires-Dist: coverage (==6.1.1) ; (python_version < "3.7" and python_version >= "3.6") and extra == 'all-strict'
Requires-Dist: pytest (==4.6.0) ; (python_version < "3.7.0" and python_version >= "3.6.0") and extra == 'all-strict'
Requires-Dist: coverage (==6.1.1) ; (python_version < "3.8" and python_version >= "3.7") and extra == 'all-strict'
Requires-Dist: coverage (==6.1.1) ; (python_version < "3.9" and python_version >= "3.8") and extra == 'all-strict'
Requires-Dist: coverage (==6.1.1) ; (python_version >= "3.10") and extra == 'all-strict'
Requires-Dist: pytest (==6.2.5) ; (python_version >= "3.10.0") and extra == 'all-strict'
Requires-Dist: pytest-cov (==3.0.0) ; (python_version >= "3.6.0") and extra == 'all-strict'
Requires-Dist: coverage ; (python_version < "2.7" and python_version >= "2.6") and extra == 'all'
Requires-Dist: pytest ; (python_version < "2.8.0" and python_version >= "2.7.0") and extra == 'all'
Requires-Dist: pytest-cov ; (python_version < "2.8.0" and python_version >= "2.7.0") and extra == 'all'
Requires-Dist: coverage ; (python_version < "3.10" and python_version >= "3.9") and extra == 'all'
Requires-Dist: pytest ; (python_version < "3.10.0" and python_version >= "3.7.0") and extra == 'all'
Requires-Dist: coverage ; (python_version < "3.4" and python_version >= "2.7") and extra == 'all'
Requires-Dist: coverage ; (python_version < "3.5" and python_version >= "3.4") and extra == 'all'
Requires-Dist: pytest ; (python_version < "3.5.0" and python_version >= "3.4.0") and extra == 'all'
Requires-Dist: pytest-cov ; (python_version < "3.5.0" and python_version >= "3.4.0") and extra == 'all'
Requires-Dist: coverage ; (python_version < "3.6" and python_version >= "3.5") and extra == 'all'
Requires-Dist: pytest ; (python_version < "3.6.0" and python_version >= "3.5.0") and extra == 'all'
Requires-Dist: pytest-cov ; (python_version < "3.6.0" and python_version >= "3.5.0") and extra == 'all'
Requires-Dist: coverage ; (python_version < "3.7" and python_version >= "3.6") and extra == 'all'
Requires-Dist: pytest ; (python_version < "3.7.0" and python_version >= "3.6.0") and extra == 'all'
Requires-Dist: coverage ; (python_version < "3.8" and python_version >= "3.7") and extra == 'all'
Requires-Dist: coverage ; (python_version < "3.9" and python_version >= "3.8") and extra == 'all'
Requires-Dist: coverage ; (python_version >= "3.10") and extra == 'all'
Requires-Dist: pytest ; (python_version >= "3.10.0") and extra == 'all'
Requires-Dist: pytest-cov ; (python_version >= "3.6.0") and extra == 'all'
Provides-Extra: optional
Provides-Extra: optional-strict
Provides-Extra: runtime-strict
Provides-Extra: tests
Requires-Dist: codecov ; extra == 'tests'
Requires-Dist: pytest-timeout ; extra == 'tests'
Requires-Dist: xdoctest ; extra == 'tests'
Provides-Extra: tests-strict
Requires-Dist: codecov (==2.0.15) ; extra == 'tests-strict'
Requires-Dist: pytest-timeout (==1.4.2) ; extra == 'tests-strict'
Requires-Dist: xdoctest (==0.15.0) ; extra == 'tests-strict'
Requires-Dist: coverage (==4.5) ; (python_version < "2.7" and python_version >= "2.6") and extra == 'tests-strict'
Requires-Dist: pytest-cov (==2.8.1) ; (python_version < "2.8.0" and python_version >= "2.7.0") and extra == 'tests-strict'
Requires-Dist: pytest (<=4.6.11,==4.6.0) ; (python_version < "2.8.0" and python_version >= "2.7.0") and extra == 'tests-strict'
Requires-Dist: coverage (==5.3.1) ; (python_version < "3.10" and python_version >= "3.9") and extra == 'tests-strict'
Requires-Dist: pytest (==4.6.0) ; (python_version < "3.10.0" and python_version >= "3.7.0") and extra == 'tests-strict'
Requires-Dist: coverage (==5.3.1) ; (python_version < "3.4" and python_version >= "2.7") and extra == 'tests-strict'
Requires-Dist: coverage (==4.3.4) ; (python_version < "3.5" and python_version >= "3.4") and extra == 'tests-strict'
Requires-Dist: pytest-cov (==2.8.1) ; (python_version < "3.5.0" and python_version >= "3.4.0") and extra == 'tests-strict'
Requires-Dist: pytest (<=4.6.11,==4.6.0) ; (python_version < "3.5.0" and python_version >= "3.4.0") and extra == 'tests-strict'
Requires-Dist: coverage (==5.3.1) ; (python_version < "3.6" and python_version >= "3.5") and extra == 'tests-strict'
Requires-Dist: pytest-cov (==2.9.0) ; (python_version < "3.6.0" and python_version >= "3.5.0") and extra == 'tests-strict'
Requires-Dist: pytest (<=6.1.2,==4.6.0) ; (python_version < "3.6.0" and python_version >= "3.5.0") and extra == 'tests-strict'
Requires-Dist: coverage (==6.1.1) ; (python_version < "3.7" and python_version >= "3.6") and extra == 'tests-strict'
Requires-Dist: pytest (==4.6.0) ; (python_version < "3.7.0" and python_version >= "3.6.0") and extra == 'tests-strict'
Requires-Dist: coverage (==6.1.1) ; (python_version < "3.8" and python_version >= "3.7") and extra == 'tests-strict'
Requires-Dist: coverage (==6.1.1) ; (python_version < "3.9" and python_version >= "3.8") and extra == 'tests-strict'
Requires-Dist: coverage (==6.1.1) ; (python_version >= "3.10") and extra == 'tests-strict'
Requires-Dist: pytest (==6.2.5) ; (python_version >= "3.10.0") and extra == 'tests-strict'
Requires-Dist: pytest-cov (==3.0.0) ; (python_version >= "3.6.0") and extra == 'tests-strict'
Requires-Dist: coverage ; (python_version < "2.7" and python_version >= "2.6") and extra == 'tests'
Requires-Dist: pytest ; (python_version < "2.8.0" and python_version >= "2.7.0") and extra == 'tests'
Requires-Dist: pytest-cov ; (python_version < "2.8.0" and python_version >= "2.7.0") and extra == 'tests'
Requires-Dist: coverage ; (python_version < "3.10" and python_version >= "3.9") and extra == 'tests'
Requires-Dist: pytest ; (python_version < "3.10.0" and python_version >= "3.7.0") and extra == 'tests'
Requires-Dist: coverage ; (python_version < "3.4" and python_version >= "2.7") and extra == 'tests'
Requires-Dist: coverage ; (python_version < "3.5" and python_version >= "3.4") and extra == 'tests'
Requires-Dist: pytest ; (python_version < "3.5.0" and python_version >= "3.4.0") and extra == 'tests'
Requires-Dist: pytest-cov ; (python_version < "3.5.0" and python_version >= "3.4.0") and extra == 'tests'
Requires-Dist: coverage ; (python_version < "3.6" and python_version >= "3.5") and extra == 'tests'
Requires-Dist: pytest ; (python_version < "3.6.0" and python_version >= "3.5.0") and extra == 'tests'
Requires-Dist: pytest-cov ; (python_version < "3.6.0" and python_version >= "3.5.0") and extra == 'tests'
Requires-Dist: coverage ; (python_version < "3.7" and python_version >= "3.6") and extra == 'tests'
Requires-Dist: pytest ; (python_version < "3.7.0" and python_version >= "3.6.0") and extra == 'tests'
Requires-Dist: coverage ; (python_version < "3.8" and python_version >= "3.7") and extra == 'tests'
Requires-Dist: coverage ; (python_version < "3.9" and python_version >= "3.8") and extra == 'tests'
Requires-Dist: coverage ; (python_version >= "3.10") and extra == 'tests'
Requires-Dist: pytest ; (python_version >= "3.10.0") and extra == 'tests'
Requires-Dist: pytest-cov ; (python_version >= "3.6.0") and extra == 'tests'
